mycalc/calculator.py
sanghyun2052733-1.0.1.dist-info/METADATA
sanghyun2052733-1.0.1.dist-info/WHEEL
sanghyun2052733-1.0.1.dist-info/top_level.txt
sanghyun2052733-1.0.1.dist-info/RECORD
