Metadata-Version: 2.1
Name: sanghyun2052733
Version: 1.0.1
Summary: nice calc
Home-page: https://github.com/sanghyun27/oss
Download-URL: https://github.com/sanghyun27/oss
Author: kim
License: UNKNOWN
Platform: UNKNOWN
Classifier: Programming Language :: Python :: 3
